example-slackapp/__init__.py
example-slackapp/__main__.py
example-slackapp/app.py
example-slackapp/app_data.py
example-slackapp/app_errors.py
example-slackapp/log.py
example-slackapp/sessions.py
example-slackapp/api/__init__.py
example-slackapp/api/api_health.py
example-slackapp/api/api_slack.py
example-slackapp/commands/__init__.py
example-slackapp/commands/demo/__init__.py
example-slackapp/commands/demo/apptest_block.py
example-slackapp/commands/demo/apptest_dialog.py
example-slackapp/commands/demo/apptest_modal.py
example-slackapp/commands/demo/apptest_modal_update.py
example-slackapp/commands/demo/apptest_modal_update_async.py
example-slackapp/commands/demo/cli.py
example-slackapp/commands/demo/main.py
example-slackapp/commands/ping/__init__.py
example-slackapp/commands/ping/cli.py
example-slackapp/commands/ping/main.py
example-slackapp/commands/ping/ping_exec.py
slackapptk/__init__.py
slackapptk/app.py
slackapptk/cli.py
slackapptk/config.py
slackapptk/errors.py
slackapptk/messenger.py
slackapptk/modal.py
slackapptk/response.py
slackapptk/verify_request.py
slackapptk/flask/__init__.py
slackapptk/flask/sessions.py
slackapptk/flask/verify_request.py
slackapptk/request/__init__.py
slackapptk/request/action_event.py
slackapptk/request/all.py
slackapptk/request/any.py
slackapptk/request/command.py
slackapptk/request/event.py
slackapptk/request/interactive.py
slackapptk/request/outmoded.py
slackapptk/request/select.py
slackapptk/request/view.py
slackapptk/request/view_inputs.py
slackapptk/utils/__init__.py
slackapptk/utils/matcher.py
slackapptk/utils/validators.py
slackapptk/web/__init__.py
slackapptk/web/classes/__init__.py
slackapptk/web/classes/objects.py
slackapptk/web/classes/view.py
slackapptk-2.0.3.dist-info/LICENSE.txt
slackapptk-2.0.3.dist-info/METADATA
slackapptk-2.0.3.dist-info/WHEEL
slackapptk-2.0.3.dist-info/top_level.txt
slackapptk-2.0.3.dist-info/RECORD
