Metadata-Version: 2.1
Name: slackapptk
Version: 2.0.3
Summary: Toolkit for creating Slack apps
Home-page: UNKNOWN
Author: Jeremy Schulman
License: UNKNOWN
Platform: UNKNOWN
Requires-Dist: first
Requires-Dist: pyee
Requires-Dist: aiohttp (==3.6.3)
Requires-Dist: slackclient (==2.9.2)
